{"type":"Topology","objects":{"features":{"type":"GeometryCollection","geometries":[{"arcs":[[0,1,2,3]],"type":"Polygon","properties":{"submap":0,"name":"Koblenz | Ahrweiler","code":"Koblenz | Ahrweiler","id":"305"}},{"arcs":[[4,5,6]],"type":"Polygon","properties":{"submap":0,"name":"Koblenz | Altenkirchen","code":"Koblenz | Altenkirchen","id":"306"}},{"arcs":[[7,8,9,10,11,12]],"type":"Polygon","properties":{"submap":0,"name":"Koblenz | Bad Kreuznach","code":"Koblenz | Bad Kreuznach","id":"307"}},{"arcs":[[-12,13,14,15,16,17]],"type":"Polygon","properties":{"submap":0,"name":"Koblenz | Birkenfeld","code":"Koblenz | Birkenfeld","id":"308"}},{"arcs":[[18,19,20,21]],"type":"Polygon","properties":{"submap":0,"name":"Koblenz | Cochem-Zell","code":"Koblenz | Cochem-Zell","id":"309"}},{"arcs":[[22,23,24]],"type":"Polygon","properties":{"submap":0,"name":"Koblenz | Koblenz Coblenz Städte","code":"Koblenz | Koblenz Coblenz Städte","id":"310"}},{"arcs":[[25,26,-24,27,28,-22,29,-2]],"type":"Polygon","properties":{"submap":0,"name":"Koblenz | Mayen-Koblenz","code":"Koblenz | Mayen-Koblenz","id":"311"}},{"arcs":[[-6,30,-26,-1,31]],"type":"Polygon","properties":{"submap":0,"name":"Koblenz | Neuwied","code":"Koblenz | Neuwied","id":"312"}},{"arcs":[[32,33,-13,-18,34,-19,-29]],"type":"Polygon","properties":{"submap":0,"name":"Koblenz | Rhein-Hunsrück","code":"Koblenz | Rhein-Hunsrück","id":"313"}},{"arcs":[[35,36,-33,-28,-23,37]],"type":"Polygon","properties":{"submap":0,"name":"Koblenz | Rhein-Lahn","code":"Koblenz | Rhein-Lahn","id":"314"}},{"arcs":[[-38,-25,-27,-31,-5,38]],"type":"Polygon","properties":{"submap":0,"name":"Koblenz | Westerwaldkreis","code":"Koblenz | Westerwaldkreis","id":"315"}},{"arcs":[[39,40,41,42,43,-9]],"type":"Polygon","properties":{"submap":0,"name":"Rheinhessen-Pfalz | Alzey-Worms","code":"Rheinhessen-Pfalz | Alzey-Worms","id":"316"}},{"arcs":[[44,45,46,47,48,49,50,51,52,53,-43]],"type":"Polygon","properties":{"submap":0,"name":"Rheinhessen-Pfalz | Bad Dürkheim","code":"Rheinhessen-Pfalz | Bad Dürkheim","id":"317"}},{"arcs":[[-44,-54,54,55,-10]],"type":"Polygon","properties":{"submap":0,"name":"Rheinhessen-Pfalz | Donnersbergkreis","code":"Rheinhessen-Pfalz | Donnersbergkreis","id":"318"}},{"arcs":[[56,57,58]],"type":"Polygon","properties":{"submap":0,"name":"Rheinhessen-Pfalz | Frankenthal Städte","code":"Rheinhessen-Pfalz | Frankenthal Städte","id":"319"}},{"arcs":[[59,60,61]],"type":"Polygon","properties":{"submap":0,"name":"Rheinhessen-Pfalz | Germersheim","code":"Rheinhessen-Pfalz | Germersheim","id":"320"}},{"arcs":[[-52,62]],"type":"Polygon","properties":{"submap":0,"name":"Rheinhessen-Pfalz | Kaiserslautern Städte","code":"Rheinhessen-Pfalz | Kaiserslautern Städte","id":"321"}},{"arcs":[[-55,-53,-63,-51,63,64,65]],"type":"Polygon","properties":{"submap":0,"name":"Rheinhessen-Pfalz | Kaiserslautern","code":"Rheinhessen-Pfalz | Kaiserslautern","id":"322"}},{"arcs":[[-11,-56,-66,66,-14]],"type":"Polygon","properties":{"submap":0,"name":"Rheinhessen-Pfalz | Kusel","code":"Rheinhessen-Pfalz | Kusel","id":"323"}},{"arcs":[[67,68,-49]],"type":"Polygon","properties":{"submap":0,"name":"Rheinhessen-Pfalz | Landau Städte","code":"Rheinhessen-Pfalz | Landau Städte","id":"324"}},{"arcs":[[69,70,-57]],"type":"Polygon","properties":{"submap":0,"name":"Rheinhessen-Pfalz | Ludwigshafen Städte","code":"Rheinhessen-Pfalz | Ludwigshafen Städte","id":"325"}},{"arcs":[[-37,71,72,73,-40,-8,-34]],"type":"Polygon","properties":{"submap":0,"name":"Rheinhessen-Pfalz | Mainz-Bingen","code":"Rheinhessen-Pfalz | Mainz-Bingen","id":"326"}},{"arcs":[[74,-73]],"type":"Polygon","properties":{"submap":0,"name":"Rheinhessen-Pfalz | Mainz Städte","code":"Rheinhessen-Pfalz | Mainz Städte","id":"327"}},{"arcs":[[-47,75,76]],"type":"Polygon","properties":{"submap":0,"name":"Rheinhessen-Pfalz | Neustadt Städte","code":"Rheinhessen-Pfalz | Neustadt Städte","id":"328"}},{"arcs":[[77,-58,-71,78,79,80,-62,81,-76,-46,82]],"type":"Polygon","properties":{"submap":0,"name":"Rheinhessen-Pfalz | Rhein-Pfalz-Kreis","code":"Rheinhessen-Pfalz | Rhein-Pfalz-Kreis","id":"329"}},{"arcs":[[-80,83]],"type":"Polygon","properties":{"submap":0,"name":"Rheinhessen-Pfalz | Speyer Spires Städte","code":"Rheinhessen-Pfalz | Speyer Spires Städte","id":"330"}},{"arcs":[[-77,-82,-61,84,85,-68,-48]],"type":"Polygon","properties":{"submap":0,"name":"Rheinhessen-Pfalz | Südliche Weinstraße","code":"Rheinhessen-Pfalz | Südliche Weinstraße","id":"331"}},{"arcs":[[-64,-50,-69,-86,86,87,88]],"type":"Polygon","properties":{"submap":0,"name":"Rheinhessen-Pfalz | Südwestpfalz","code":"Rheinhessen-Pfalz | Südwestpfalz","id":"332"}},{"arcs":[[89,-83,-45,-42]],"type":"Polygon","properties":{"submap":0,"name":"Rheinhessen-Pfalz | Worms Städte","code":"Rheinhessen-Pfalz | Worms Städte","id":"333"}},{"arcs":[[90,-88]],"type":"Polygon","properties":{"submap":0,"name":"Rheinhessen-Pfalz | Zweibrücken Städte","code":"Rheinhessen-Pfalz | Zweibrücken Städte","id":"334"}},{"arcs":[[-20,-35,-17,91,92,93]],"type":"Polygon","properties":{"submap":0,"name":"Trier | Bernkastel-Wittlich","code":"Trier | Bernkastel-Wittlich","id":"335"}},{"arcs":[[94,-93,95,96]],"type":"Polygon","properties":{"submap":0,"name":"Trier | Bitburg-Prüm","code":"Trier | Bitburg-Prüm","id":"336"}},{"arcs":[[-92,-16,97,-96],[98]],"type":"Polygon","properties":{"submap":0,"name":"Trier | Trier-Saarburg","code":"Trier | Trier-Saarburg","id":"337"}},{"arcs":[[-99]],"type":"Polygon","properties":{"submap":0,"name":"Trier | Trier Städte","code":"Trier | Trier Städte","id":"338"}},{"arcs":[[-3,-30,-21,-94,-95,99]],"type":"Polygon","properties":{"submap":0,"name":"Trier | Vulkaneifel","code":"Trier | Vulkaneifel","id":"339"}}]}},"arcs":[[[678,1563],[80,-139]],[[758,1424],[-53,-78],[-112,3],[-54,-50]],[[539,1299],[-29,-40],[-83,48]],[[427,1307],[-35,80],[32,48],[125,71],[30,37],[99,20]],[[1189,1638],[-59,11],[-42,-23],[-90,40],[-20,-99]],[[978,1567],[-34,26],[-64,-28],[-66,80]],[[814,1645],[99,55],[36,2],[63,106],[125,-28],[4,-70],[48,-72]],[[998,976],[102,-67],[38,-95]],[[1138,814],[-35,-74]],[[1103,740],[-66,5],[-43,-36],[-11,-63]],[[983,646],[-113,58]],[[870,704],[-67,44],[-11,96]],[[792,844],[60,5],[146,127]],[[870,704],[-52,-110],[-50,6],[-51,-44]],[[717,556],[-63,49],[-38,-5],[-52,42]],[[564,642],[8,46]],[[572,688],[52,84],[86,73],[-27,29]],[[683,874],[107,8],[2,-38]],[[784,1129],[-18,-138],[-94,-43]],[[672,948],[-41,28],[-24,60],[-73,29]],[[534,1065],[0,130],[55,42]],[[589,1237],[108,-17],[87,-91]],[[974,1318],[-52,-62]],[[922,1256],[-46,-10],[-29,71],[55,42],[56,-21]],[[958,1338],[16,-20]],[[758,1424],[90,-61],[70,53]],[[918,1416],[40,-78]],[[922,1256],[20,-45]],[[942,1211],[-76,6],[-82,-88]],[[589,1237],[-50,62]],[[978,1567],[-14,-127],[-46,-24]],[[678,1563],[89,23],[1,53],[46,6]],[[942,1211],[79,-153]],[[1021,1058],[-64,-46],[41,-36]],[[683,874],[-11,74]],[[1151,1361],[56,-31],[35,-94],[-131,-67],[6,-89],[-92,-39]],[[1025,1041],[-4,17]],[[974,1318],[32,12],[78,-25],[30,61],[37,-5]],[[1189,1638],[74,-101],[-68,-33],[-41,-58],[-3,-85]],[[1138,814],[98,61],[80,-122],[92,36]],[[1408,789],[26,-68]],[[1434,721],[-60,0],[-55,-41],[-2,-91]],[[1317,589],[-64,32]],[[1253,621],[-30,61],[-120,58]],[[1317,589],[15,-3]],[[1332,586],[-7,-132],[25,-128]],[[1350,326],[-42,12],[-12,51],[-52,15],[-85,-53]],[[1159,351],[-37,-29]],[[1122,322],[-42,6]],[[1080,328],[-21,10]],[[1059,338],[-1,31]],[[1058,369],[10,7]],[[1068,376],[81,69],[-9,49]],[[1140,494],[47,30],[66,97]],[[1140,494],[-29,40],[-51,-19],[-82,71]],[[978,586],[5,60]],[[1417,542],[-69,-52]],[[1348,490],[19,67],[49,16]],[[1416,573],[1,-31]],[[1411,270],[-28,-79],[-5,-67],[-41,-91],[-33,-33],[-110,34]],[[1194,34],[16,78],[47,44],[62,-4],[-9,140],[44,20]],[[1354,312],[57,-42]],[[1058,369],[-74,36],[-22,52],[64,37],[50,-37],[-8,-81]],[[1059,338],[-42,19],[-175,0],[-47,27]],[[795,384],[-4,3]],[[791,387],[32,81],[52,54],[66,18],[37,46]],[[791,387],[-67,18],[10,78],[-17,73]],[[1122,322],[-40,-25]],[[1082,297],[-2,31]],[[1417,542],[30,-89]],[[1447,453],[-38,-16],[-61,53]],[[1025,1041],[63,-93],[61,5],[133,54]],[[1282,1007],[-24,-32],[55,-57],[60,-1]],[[1373,917],[-2,-49],[37,-79]],[[1282,1007],[32,-5],[59,-85]],[[1350,326],[0,-4]],[[1350,322],[-169,9],[-22,20]],[[1412,594],[4,-21]],[[1447,453],[-1,-97]],[[1446,356],[-2,-53]],[[1444,303],[-33,-33]],[[1354,312],[-4,10]],[[1332,586],[80,8]],[[1446,356],[-2,-53]],[[1194,34],[-107,40]],[[1087,74],[22,125],[-27,98]],[[1087,74],[-53,16],[-79,-17],[-86,49],[-52,82],[-75,14]],[[742,218],[57,61],[-9,56]],[[790,335],[5,49]],[[1434,721],[-55,-52],[33,-75]],[[742,218],[-19,44],[67,73]],[[572,688],[-101,84],[-1,80],[-103,34]],[[367,886],[-4,165]],[[363,1051],[98,44],[73,-30]],[[190,1281],[53,-36],[56,-79],[-30,-53],[94,-62]],[[367,886],[-113,-44],[-33,-34]],[[221,808],[-144,66],[-11,56],[-39,10],[-27,83],[4,69],[44,64],[-12,44],[64,28],[16,50],[74,3]],[[564,642],[-102,-31],[-75,-51],[-151,-30],[-82,43],[37,87],[49,47],[9,77],[-28,24]],[[364,814],[-31,-16],[-55,-102],[47,-4],[55,39],[-16,83]],[[190,1281],[23,36],[80,17],[76,-41],[58,14]]],"transform":{"scale":[0.0016326083706256558,0.001056347508475151],"translate":[6.111746113900427,48.968763500037745]}}