{"type":"Topology","objects":{"features":{"type":"GeometryCollection","geometries":[{"arcs":[[0,1,2]],"type":"Polygon","properties":{"submap":0,"name":"Elena","code":"Elena","id":"228"}},{"arcs":[[3,4,5,6]],"type":"Polygon","properties":{"submap":0,"name":"Gorna Orhyahovitsa","code":"Gorna Orhyahovitsa","id":"229"}},{"arcs":[[7,8,-5,9]],"type":"Polygon","properties":{"submap":0,"name":"Lyaskovets","code":"Lyaskovets","id":"230"}},{"arcs":[[10,11,12,13,14,15]],"type":"Polygon","properties":{"submap":0,"name":"Pavlikeni","code":"Pavlikeni","id":"231"}},{"arcs":[[16,-7,17,-11,18,19]],"type":"Polygon","properties":{"submap":0,"name":"Polski Trambesh","code":"Polski Trambesh","id":"232"}},{"arcs":[[20,21,-10,-4,-17]],"type":"Polygon","properties":{"submap":0,"name":"Strazhitsa","code":"Strazhitsa","id":"233"}},{"arcs":[[-14,22]],"type":"Polygon","properties":{"submap":0,"name":"Suhindol","code":"Suhindol","id":"234"}},{"arcs":[[-19,-16,23]],"type":"Polygon","properties":{"submap":0,"name":"Svishtov","code":"Svishtov","id":"235"}},{"arcs":[[-6,-9,24,-2,25,-12,-18]],"type":"Polygon","properties":{"submap":0,"name":"Veliko Tarnovo","code":"Veliko Tarnovo","id":"236"}},{"arcs":[[26,-3,-25,-8,-22]],"type":"Polygon","properties":{"submap":0,"name":"Zlataritsa","code":"Zlataritsa","id":"237"}}]}},"arcs":[[[906,290],[74,-46],[-34,-46],[-65,-33],[-1,-45],[-78,-69],[-95,-28],[-61,20],[-79,-8]],[[567,35],[40,94],[-28,25],[0,106],[112,5]],[[691,265],[136,69],[23,-39],[56,-5]],[[623,702],[27,-109],[69,-1],[-7,-59]],[[712,533],[-72,-69],[-84,-30]],[[556,434],[-56,15],[-36,94],[30,78]],[[494,621],[82,15],[47,66]],[[785,469],[-53,-8],[-67,-94]],[[665,367],[-82,-5],[-27,72]],[[712,533],[29,11],[44,-75]],[[297,810],[-4,-73],[40,-65],[62,-41]],[[395,631],[-38,-26],[-28,-79],[7,-56],[-48,-24],[-38,42],[-39,-51]],[[211,437],[-38,-2]],[[173,435],[-14,78],[-58,42],[-26,101]],[[75,656],[65,42],[5,52]],[[145,750],[40,41],[112,19]],[[645,755],[-22,-53]],[[494,621],[-99,10]],[[297,810],[103,100]],[[400,910],[33,-4],[-9,-87],[95,-43],[36,16],[55,-48],[35,11]],[[645,755],[114,-1],[18,-54],[70,-8],[71,-143],[-32,-33],[-14,-81]],[[872,435],[-87,34]],[[173,435],[-62,-23],[-60,25],[-51,78],[75,141]],[[145,750],[-81,97],[30,21],[20,84],[-9,96],[-25,52],[63,42],[102,-73],[98,20],[39,-53],[-34,-39],[52,-87]],[[665,367],[26,-102]],[[567,35],[-54,-35],[-31,22],[-15,71],[30,21],[-12,63],[-61,33],[34,69],[-5,40],[-102,37],[-135,7],[-5,74]],[[872,435],[64,-104],[-30,-41]]],"transform":{"scale":[0.0011124688751842351,0.0008324790734019521],"translate":[25.107034683227653,42.74988937377941]}}